LICENSE
README.md
setup.py
amiclimate/__init__.py
amiclimate/amix.py
amiclimate/ipcc.py
amiclimate/un.py
amiclimate.egg-info/PKG-INFO
amiclimate.egg-info/SOURCES.txt
amiclimate.egg-info/dependency_links.txt
amiclimate.egg-info/entry_points.txt
amiclimate.egg-info/not-zip-safe
amiclimate.egg-info/top_level.txt
test/test_all.py
test/test_un.py