Metadata-Version: 2.1
Name: amiclimate
Version: 0.0.1a2
Summary: processes UN/IPCC and UNFCCC documents
Home-page: https://github.com/petermr/amiclimate
Author: Peter Murray-Rust
Author-email: petermurrayrust@googlemail.com
License: Apache2
Keywords: text and data mining
Classifier: Development Status :: 3 - Alpha
Classifier: Intended Audience :: Developers
Classifier: License :: OSI Approved :: Apache Software License
Classifier: Natural Language :: English
Classifier: Programming Language :: Python :: 3.4
Classifier: Programming Language :: Python :: 3.5
Classifier: Programming Language :: Python :: 3.6
Classifier: Programming Language :: Python :: 3.8
Requires-Python: >=3.7
License-File: LICENSE
